{"authors": ["BBC News", "www.facebook.com"], "date_download": "2025-05-19 14:25:29", "date_modify": "2025-05-19 14:25:29", "date_publish": "2015-03-10 11:19:24", "description": "A woman is treated by paramedics after collapsing following a fire in the kitchen of her Renfrewshire home.", "filename": "news_uk-scotland-glasgow-west-31814312_1747664729.html", "image_url": "https://ichef.bbci.co.uk/ace/branded_news/1200/mcs/media/images/81539000/jpg/_81539808_fire5b.jpg", "language": "en", "localpath": "C:\\Users\\vopha/news-please-repo//data/2025/05/19/bbc.com/news_uk-scotland-glasgow-west-31814312_1747664729.html", "title": "Woman collapses after kitchen fire in Kilbarchan", "title_page": "Woman collapses after kitchen fire in Kilbarchan - BBC News", "title_rss": "NULL", "source_domain": "bbc.com", "maintext": "A woman has been treated by paramedics after collapsing following a fire in the kitchen of her Renfrewshire home.\nFire crews were called to the flat in Wheatlands Drive, Kilbarchan, at about 20:15 on Monday.\nThey extinguished the blaze and provided treatment to the woman while awaiting paramedics. She did not need to go to hospital.\nThe fire service said an early 999 call meant crews were able to prevent the blaze from spreading to other rooms.", "url": "https://www.bbc.com/news/uk-scotland-glasgow-west-31814312"}