{"authors": ["BBC Sport", "www.facebook.com"], "date_download": "2025-05-21 05:04:19", "date_modify": "2025-05-21 05:04:19", "date_publish": "2025-04-04 08:01:14", "description": "Crystal Palace vs Brighton: Did you know?", "filename": "sport_football_articles_cg41qendknro_1747803859.html", "image_url": "https://ichef.bbci.co.uk/ace/branded_sport/1200/cpsprodpb/bb5a/live/c9db8b70-0eea-11f0-9471-fd068d782b6b.jpg", "language": "en", "localpath": "C:\\Users\\vopha/news-please-repo//data/2025/05/21/bbc.com/sport_football_articles_cg41qendknro_1747803859.html", "title": "Crystal Palace vs Brighton: Did you know?", "title_page": "Crystal Palace vs Brighton: Did you know? - BBC Sport", "title_rss": "NULL", "source_domain": "bbc.com", "maintext": "Following their 3-1 win at Amex Stadium in December, Crystal Palace are looking to complete their first league double over Brighton since 1932-33 and their first time in the top flight.\nEach of the past five Premier League meetings between Crystal Palace and Brighton at Selhurst Park has finished 1-1. No specific fixture in English top-flight history has finished with the same scoreline on six consecutive occasions before.", "url": "https://www.bbc.com/sport/football/articles/cg41qendknro"}