{"authors": ["BBC Sport", "www.facebook.com"], "date_download": "2025-05-20 11:44:19", "date_modify": "2025-05-20 11:44:19", "date_publish": "2023-08-06 14:17:35", "description": "Man Utd: Andre Onana happy to accept criticism for goals conceded", "filename": "sport_articles_crgn8ljk579o_1747741459.html", "image_url": "https://ichef.bbci.co.uk/ace/branded_sport/1200/cpsprodpb/6cfa/live/cb17df10-3463-11ee-b655-099f29f3c290.jpg", "language": "en", "localpath": "C:\\Users\\vopha/news-please-repo//data/2025/05/20/bbc.com/sport_articles_crgn8ljk579o_1747741459.html", "title": "Man Utd: Andre Onana happy to accept criticism for goals conceded", "title_page": "Man Utd: Andre Onana happy to accept criticism for goals conceded - BBC Sport", "title_rss": "NULL", "source_domain": "bbc.com", "maintext": "Simon Stone, BBC Sport\nNew United goalkeeper Andre Onana took some criticism for Lens' goal in the 3-1 pre-season win at Old Trafford on Saturday, even though it was not actually his fault.\nOnana was beaten by a 50-yard chip from Florian Sotoca after Diogo Dalot had needlessly given the ball away inside his own half.\n\"We can always be better,\" said the Cameroon international. \"Some things we have to try to fix.\n\"I am responsible for everything, especially the goals we concede. I am the big man in the back so I take all the criticism.\"\nOnana has certainly made an impact since his arrival from Inter Milan last month, with the vast majority of a crowd in excess of 50,000 at Old Trafford enthusiastically getting behind the 27-year-old.", "url": "https://www.bbc.com/sport/articles/crgn8ljk579o"}