{"authors": ["BBC Sport", "www.facebook.com"], "date_download": "2025-05-20 11:41:07", "date_modify": "2025-05-20 11:41:07", "date_publish": "2023-08-06 18:04:58", "description": "Hibernian 2-3 St Mirren: Have your say", "filename": "sport_articles_cnlyvjxg24go_1747741267.html", "image_url": "https://ichef.bbci.co.uk/ace/branded_sport/1200/cpsprodpb/3d5a/live/a470cc80-3483-11ee-bde6-7ffba94c56ae.jpg", "language": "en", "localpath": "C:\\Users\\vopha/news-please-repo//data/2025/05/20/bbc.com/sport_articles_cnlyvjxg24go_1747741267.html", "title": "Hibernian 2-3 St Mirren: Have your say", "title_page": "Hibernian 2-3 St Mirren: Have your say - BBC Sport", "title_rss": "NULL", "source_domain": "bbc.com", "maintext": "St Mirren got their Scottish Premiership campaign off to a great start with a win at Easter Road.\nWere you at the game, or did you see it on TV? Give us your thoughts here.", "url": "https://www.bbc.com/sport/articles/cnlyvjxg24go"}