{"authors": ["BBC Sport", "www.facebook.com"], "date_download": "2025-05-21 04:06:33", "date_modify": "2025-05-21 04:06:33", "date_publish": "2024-12-29 00:00:00", "description": "Bradford come from behind against Chesterfield to make it back-to-back wins in League Two", "filename": "sport_football_live_cdekxpj958dt_1747800393.html", "image_url": "https://static.files.bbci.co.uk/ws/simorgh-assets/public/sport/images/metadata/poster-1024x576.png", "language": "en", "localpath": "C:\\Users\\vopha/news-please-repo//data/2025/05/21/bbc.com/sport_football_live_cdekxpj958dt_1747800393.html", "title": "Bradford come from behind against Chesterfield to make it back-to-back wins in League Two", "title_page": "Bradford come from behind against Chesterfield to make it back-to-back wins in League Two - BBC Sport", "title_rss": "NULL", "source_domain": "bbc.com", "maintext": "Bradford City have won each of their last four Football League games against Chesterfield, keeping a clean sheet in each of those matches in the process.\nChesterfield have lost on each of their last two Football League trips to Bradford, with this their first such visit since a 2-0 loss in January 2017.\nBradford are unbeaten in their final league game of the year in each of the last eight years (W4 D4), keeping a clean sheet in five of the last six years.\nChesterfield have drawn six of their last seven final Football League games of the year (L1), whilst they’ve scored just one goal in total across their last four such matches.", "url": "https://www.bbc.com/sport/football/live/cdekxpj958dt"}