{"authors": ["BBC Sport", "www.facebook.com"], "date_download": "2025-04-26 04:28:27", "date_modify": "2025-04-26 04:28:27", "date_publish": "2025-03-02 09:16:08", "description": "Spain's Marc Marquez completes a double with victory in the opening race of the MotoGP season in Thailand.", "filename": "sport_motorsport_articles_c15qng2lqg3o_1745641707.html", "image_url": "https://ichef.bbci.co.uk/ace/branded_sport/1200/cpsprodpb/1868/live/31c54270-f745-11ef-9f40-e95ad80c0062.jpg", "language": "en", "localpath": "C:\\Users\\vopha/news-please-repo//data/2025/04/26/bbc.co.uk/sport_motorsport_articles_c15qng2lqg3o_1745641707.html", "title": "MotoGP: Ducati's Marc Marquez beats brother Alex to complete double at Thailand Grand Prix", "title_page": "MotoGP: Ducati's Marc Marquez beats brother Alex to complete double at Thailand Grand Prix - BBC Sport", "title_rss": "NULL", "source_domain": "bbc.co.uk", "maintext": "Spain's Marc Marquez completed a double with victory in the opening race of the MotoGP season at the Thailand Grand Prix.\nThe 32-year-old six-time former champion won Saturday's sprint race at the Buriram International Circuit in his first competitive outing for his new team Ducati and started Sunday's race as pole-sitter.\nAnd for the second day in a row he beat younger brother Alex into second, finishing 1.732sec clear of his 28-year-old sibling.\nAlthough Marc started strongly in the hot and humid conditions, Alex grabbed the lead in the seventh lap of the 26-lap race before his older brother regained the advantage with three laps to go to win the opening race of the season for the first time since 2014.\nThe 2022 and 2023 champion Francesco Bagnaia of Italy, who also rides for Ducati, was a further 0.666sec back for his second third place finish of the weekend.\nMarquez made the switch from Gresini Racing at the end of last season.", "url": "https://www.bbc.co.uk/sport/motorsport/articles/c15qng2lqg3o"}