{"authors": ["BBC Sport", "www.facebook.com"], "date_download": "2025-05-20 14:26:54", "date_modify": "2025-05-20 14:26:54", "date_publish": "2023-07-29 10:57:25", "description": "Wales suffer a second successive defeat of their Netball World Cup campaign as they are thumped 75-40 by Jamaica in Pool C in Cape Town.", "filename": "sport_netball_66341795_1747751214.html", "image_url": "https://ichef.bbci.co.uk/ace/branded_sport/1200/cpsprodpb/110BA/production/_130581896_gettyimages-1562108567.jpg", "language": "en", "localpath": "C:\\Users\\vopha/news-please-repo//data/2025/05/20/bbc.com/sport_netball_66341795_1747751214.html", "title": "Netball World Cup 2023: Jamaica 75-40 Wales", "title_page": "Netball World Cup 2023: Jamaica 75-40 Wales - BBC Sport", "title_rss": "NULL", "source_domain": "bbc.com", "maintext": "Wales suffered a second successive defeat of their Netball World Cup campaign as they were hammered by Jamaica in Pool C in Cape Town.\nJamaica, the 2022 Commonwealth Games silver medallists, led 23-11 after a first quarter in which Wales had rallied from an early 6-1 deficit.\nWales trailed 44-23 at half-time and were then 58-29 down as the Sunshine Girls dominated the third quarter.\nAnd there was no respite as Jamaica went on to win 75-40.\nWelsh Feathers coach Emily Handyside made one starting line-up change from their opening 61-50 defeat by hosts South Africa with Shona O'Dwyer coming in for Clare Jones at centre.\nJamaica beat Welsh Feathers' next opponents Sri Lanka 105-25 in their opener.\nWelsh Feathers, who are world ranked ninth, must beat the Lionesses, ranked 15th, on Sunday (08:00 BST) to reach the classification rounds.\nJamaica head into to a showdown with South Africa later on Sunday that will determine who tops the group.", "url": "https://www.bbc.com/sport/netball/66341795"}