{"authors": ["Nick Hope", "www.facebook.com"], "date_download": "2025-05-19 15:19:06", "date_modify": "2025-05-19 15:19:06", "date_publish": "2015-02-27 12:07:19", "description": "Chris and Gabby Adcock aim to become the first British pair since 2005 to win a title at the All England Championships.", "filename": "sport_badminton_31661628_1747667946.html", "image_url": "https://ichef.bbci.co.uk/ace/branded_sport/1200/mcs/media/images/81330000/jpg/_81330892_adcocks.jpg", "language": "en", "localpath": "C:\\Users\\vopha/news-please-repo//data/2025/05/19/bbc.com/sport_badminton_31661628_1747667946.html", "title": "Adcocks target mixed doubles All England Championships title", "title_page": "Adcocks target mixed doubles All England Championships title - BBC Sport", "title_rss": "NULL", "source_domain": "bbc.com", "maintext": "Commonwealth gold medallists Chris and Gabby Adcock will try to become the first British pair since 2005 to win a title at the All England Championships this week.\nAthens Olympic silver medal-winning, external duo Nathan Robertson and Gail Emms were the last GB pair to claim an All England title, in 2005., external\nThe Adcocks, who are married, are seeded sixth.\n\"It'll be tough, but we believe we can win it,\" said Chris Adcock.", "url": "https://www.bbc.com/sport/badminton/31661628"}