{"authors": ["BBC Sport", "www.facebook.com"], "date_download": "2025-05-21 07:05:20", "date_modify": "2025-05-21 07:05:20", "date_publish": "2025-03-29 00:00:00", "description": "Fleetwood Town come from behind to beat Milton Keynes Dons 4-2 at Stadium MK.", "filename": "sport_football_live_c871z1ze57gt_1747811120.html", "image_url": "https://ichef.bbci.co.uk/ace/branded_sport/1200/cpsprodpb/1777/live/924109d0-0cc2-11f0-ba12-8d27eb561761.jpg", "language": "en", "localpath": "C:\\Users\\vopha/news-please-repo//data/2025/05/21/bbc.com/sport_football_live_c871z1ze57gt_1747811120.html", "title": "Milton Keynes Dons 2-4 Fleetwood Town", "title_page": "Milton Keynes Dons 2-4 Fleetwood Town - BBC Sport", "title_rss": "NULL", "source_domain": "bbc.com", "maintext": "MK Dons have failed to win any of their last six league games against Fleetwood Town (D3 L3), losing each of their last three in succession.\nAfter winning their last away league game against MK Dons in December 2022, Fleetwood Town will be looking to take consecutive wins at Stadium MK for the first time.\nMK Dons have won just two of their last nine home league games (D2 L5), though one did come in their last outing during a 2-1 victory over Morecambe.", "url": "https://www.bbc.com/sport/football/live/c871z1ze57gt"}