{"authors": ["BBC Sport", "www.facebook.com"], "date_download": "2025-05-20 12:39:52", "date_modify": "2025-05-20 12:39:52", "date_publish": "2023-08-03 09:29:48", "description": "Nottingham Forest: Steve Cooper's side beaten heavily by Rennes", "filename": "sport_articles_cn02d9xl54qo_1747744792.html", "image_url": "https://ichef.bbci.co.uk/ace/branded_sport/1200/cpsprodpb/37b6/live/c6795e40-31d2-11ee-9be8-bdb4cc08ba55.jpg", "language": "en", "localpath": "C:\\Users\\vopha/news-please-repo//data/2025/05/20/bbc.com/sport_articles_cn02d9xl54qo_1747744792.html", "title": "Nottingham Forest: Steve Cooper's side beaten heavily by Rennes", "title_page": "Nottingham Forest: Steve Cooper's side beaten heavily by Rennes - BBC Sport", "title_rss": "NULL", "source_domain": "bbc.com", "maintext": "Nottingham Forest's pre-season bad luck continued on Wednesday evening as they fell to a 5-0 defeat by Rennes.\nThe Ligue 1 side were 2-0 up at half-time, with both goals being scored from the penalty area.\nSteve Cooper made six changes in the second half, with Forest already 4-0 down at this point.\nEsapa Osong and Josh Powell were among those to be brought on, gaining first team experience against a strong French side.\nForest's final friendly takes place on 5 August against Eintracht Frankfurt, before they face Arsenal in their Premier League opener on 12 August.", "url": "https://www.bbc.com/sport/articles/cn02d9xl54qo"}