{"authors": ["BBC Sport", "www.facebook.com"], "date_download": "2025-05-20 14:39:04", "date_modify": "2025-05-20 14:39:04", "date_publish": "2023-07-28 12:46:18", "description": "Aston Villa unveil new away kit for 2023-24", "filename": "sport_articles_c72ez3e8jxgo_1747751944.html", "image_url": "https://ichef.bbci.co.uk/ace/branded_sport/1200/cpsprodpb/6316/live/a522bcc0-2d43-11ee-b1d7-8fdc93c2782e.jpg", "language": "en", "localpath": "C:\\Users\\vopha/news-please-repo//data/2025/05/20/bbc.com/sport_articles_c72ez3e8jxgo_1747751944.html", "title": "Villa unveil new away kit", "title_page": "Aston Villa unveil new away kit for 2023-24 - BBC Sport", "title_rss": "NULL", "source_domain": "bbc.com", "maintext": "Aston Villa have released their new away kit for the 2023-24 season.\nA statement said the \"shirt is a visual timeline print that tells the story of the club's proud journey since our foundation in 1874\".\nThe kit features the redesigned crest which pays homage to Villa's European Cup-winning team of 1982 and also appears on their home strip and training gear for the new campaign.", "url": "https://www.bbc.com/sport/articles/c72ez3e8jxgo"}