{"authors": ["BBC Sport", "www.facebook.com"], "date_download": "2025-05-20 14:24:52", "date_modify": "2025-05-20 14:24:52", "date_publish": "2023-07-29 12:08:32", "description": "Lancashire batter Rob Jones joins Worcestershire on loan for One-Day Cup ahead of permanent switch in 2024.", "filename": "sport_cricket_66349005_1747751092.html", "image_url": "https://ichef.bbci.co.uk/ace/branded_sport/1200/cpsprodpb/2538/production/_130582590_gettyimages-1523734001.jpg", "language": "en", "localpath": "C:\\Users\\vopha/news-please-repo//data/2025/05/20/bbc.com/sport_cricket_66349005_1747751092.html", "title": "Rob Jones: Worcestershire sign batter on loan for One-Day Cup", "title_page": "Rob Jones: Worcestershire sign batter on loan for One-Day Cup - BBC Sport", "title_rss": "NULL", "source_domain": "bbc.com", "maintext": "Worcestershire have signed Lancashire batter Rob Jones on loan for the One-Day Cup campaign.\nThe 27-year-old had already agreed a contract at New Road from 2024 after rejecting a new deal at Old Trafford.\n\"It's a great opportunity for Rob to get to know his new team-mates and coaches before joining us permanently,\" said, external Worcestershire CEO Ashley Giles.\nJones will be available to represent Worcestershire in the national counties fixture against Shropshire on Sunday.\nGiles added: \"We are thrilled to have Rob on board for the Metro Bank One-Day Cup ahead of his permanent move. His inclusion will undoubtedly strengthen our batting line-up, and we believe he will make a substantial impact.\"\nJones made his first-class debut for Lancashire in 2016 and has made 109 appearances in all formats for the club.", "url": "https://www.bbc.com/sport/cricket/66349005"}