{"authors": ["BBC Sport", "www.facebook.com"], "date_download": "2025-05-21 04:57:47", "date_modify": "2025-05-21 04:57:47", "date_publish": "2025-01-05 09:59:28", "description": "Tottenham sign 21-year-old Czech goalkeeper Antonin Kinsky from Slavia Prague in a deal worth about £12.5m.", "filename": "sport_football_articles_c8xjzvgwe8jo_1747803467.html", "image_url": "https://ichef.bbci.co.uk/ace/branded_sport/1200/cpsprodpb/a787/live/b0f1a6a0-cb4a-11ef-9adf-8f46e2cde704.jpg", "language": "en", "localpath": "C:\\Users\\vopha/news-please-repo//data/2025/05/21/bbc.com/sport_football_articles_c8xjzvgwe8jo_1747803467.html", "title": "Tottenham transfer news: Antonin Kinsky joins for £12.5m", "title_page": "Tottenham transfer news: Antonin Kinsky joins for £12.5m - BBC Sport", "title_rss": "NULL", "source_domain": "bbc.com", "maintext": "Tottenham have signed 21-year-old Czech goalkeeper Antonin Kinsky from Slavia Prague in a deal worth about £12.5m.\nSpurs have been without first-choice keeper Guglielmo Vicario since he fractured an ankle on 24 November during the 4-0 win over Manchester City.\nFraser Forster has been deputising for Vicario, but he missed Saturday's 2-1 defeat by Newcastle with illness, which led to a debut for 25-year-old Brandon Austin.\nSpurs have only won two of their past 11 games and are 12th in the Premier League.\nKinsky has agreed a deal until 2031 and the move is subject to the granting of international clearance and a work permit.\nAfter joining from Dukla Prague in 2021, he spent some time on loan before establishing himself at Slavia.\nThe Czech Republic Under-21 player has made 29 appearances for Slavia this season and kept 14 clean sheets.", "url": "https://www.bbc.com/sport/football/articles/c8xjzvgwe8jo"}