{"authors": ["www.facebook.com"], "date_download": "2025-05-21 05:09:58", "date_modify": "2025-05-21 05:09:58", "date_publish": "2025-04-05 00:00:00", "description": "Alex Reid's brace boosted Wealdstone to back-to-back victories as National League challengers Forest Green went down 2-1 at Grosvenor Vale.", "filename": "sport_football_live_c62x584j56nt_1747804198.html", "image_url": "https://ichef.bbci.co.uk/ace/branded_sport/1200/cpsprodpb/67b0/live/86613380-1148-11f0-b234-07dc7691c360.jpg", "language": "en", "localpath": "C:\\Users\\vopha/news-please-repo//data/2025/05/21/bbc.com/sport_football_live_c62x584j56nt_1747804198.html", "title": "Wealdstone 2-1 Forest Green Rovers", "title_page": "Wealdstone 2-1 Forest Green Rovers: Match report - BBC Sport", "title_rss": "NULL", "source_domain": "bbc.com", "maintext": "Alex Reid's brace boosted Wealdstone to back-to-back victories as National League challengers Forest Green went down 2-1 at Grosvenor Vale.\nRovers swarmed all over their hosts from the off and, after Adam May hit the bar with a free-kick, Jordon Garrick drove inside from the left and found the bottom corner in the 18th minute.\nReid ensured the scores were level heading into half-time, however, as he converted a 41st-minute penalty following a handball in the box.\nNeither side could get a full grip on proceedings when play resumed until, nine minutes from time, Reid fired in his 16th league goal of the season to win it for Wealdstone.", "url": "https://www.bbc.com/sport/football/live/c62x584j56nt"}