{"authors": ["BBC Sport", "www.facebook.com"], "date_download": "2025-05-19 15:13:42", "date_modify": "2025-05-19 15:13:42", "date_publish": "2015-02-21 13:58:31", "description": "League Two side Carlisle United sign West Ham goalkeeper Raphael Spiegel on a one-month loan deal.", "filename": "sport_football_31567232_1747667622.html", "image_url": "https://ichef.bbci.co.uk/ace/branded_sport/1200/mcs/media/images/76353000/jpg/_76353322_spiegel2.jpg", "language": "en", "localpath": "C:\\Users\\vopha/news-please-repo//data/2025/05/19/bbc.com/sport_football_31567232_1747667622.html", "title": "Raphael Spiegel: Carlisle sign West Ham keeper on loan", "title_page": "Raphael Spiegel: Carlisle sign West Ham keeper on loan - BBC Sport", "title_rss": "NULL", "source_domain": "bbc.com", "maintext": "League Two side Carlisle United have signed West Ham goalkeeper Raphael Spiegel on a one-month loan deal.\nThe 22-year-old, who is yet to make his debut for the Hammers, had spells at Crawley and Barnet earlier this season.\n\"I've watched him play a couple of times and we've been given a lot of footage to review as well,\" Carlisle goalkeeping coach Tony Caig said.\n\"He's a good size, he's mobile and vocal, and he's a Swiss Under-21 international so he has good pedigree.\"\nHe added: \"West Ham are looking for him to make that next step and an opportunity to get out and play some football provides that opening for him.\"\nSpiegel will remain at Brunton Park until after Carlisle's match against Morecambe on Saturday, 21 March.", "url": "https://www.bbc.com/sport/football/31567232"}