{"authors": ["Simon King"], "date_download": "2025-04-26 08:12:50", "date_modify": "2025-04-26 08:12:50", "date_publish": "2025-02-26 11:42:53", "description": "Simon King explains what's behind the bright orange clouds you may have noticed on Wednesday.", "filename": "weather_articles_c04zn2dned3o_1745655170.html", "image_url": "https://ichef.bbci.co.uk/ace/branded_weather/1200/cpsprodpb/3ea3/live/875ca350-f424-11ef-9822-d3d66c578726.jpg", "language": "en", "localpath": "C:\\Users\\vopha/news-please-repo//data/2025/04/26/bbc.co.uk/weather_articles_c04zn2dned3o_1745655170.html", "title": "Rare red fiery 'udder clouds' spotted in UK skies", "title_page": "Rare red fiery 'udder clouds' spotted in UK skies - BBC Weather", "title_rss": "NULL", "source_domain": "bbc.co.uk", "maintext": "Unusual mammatus clouds were spotted on Wednesday morning in parts of the United Kingdom.\nThe name mammatus comes from the Latin mamma which means 'udder' or 'breast'.\nThe bulging cloud was made to look even more dramatic with a fiery, orange glow from the sunrise.\nThese clouds are often associated with thunderstorm clouds and accompanied by rain, hail and lightning.\nMammatus is most often found at the base of a thunderstorm cloud called cumulonimbus.\nWith lots of turbulence in the cloud there are lots of up and downdrafts.\nThe downdrafts can become so severe that air is forced beneath the cloud, creating large bulges of air and water droplets.\nIf you see mammatus cloud like this, it is a sure sign of impending heavy rain, hail or a big thunderstorm.\nSome of the best examples of mammatus can be seen when the sun is low in the sky, casting light on the underside of the cloud and showing up the 'udders'.\nLots of our BBC Weather Watchers particularly in North Yorkshire, managed to capture this cloud on Wednesday morning.", "url": "https://www.bbc.co.uk/weather/articles/c04zn2dned3o"}