{"authors": ["BBC Weather"], "date_download": "2025-04-26 08:01:28", "date_modify": "2025-04-26 08:01:28", "date_publish": "2025-02-26 17:31:38", "description": "As we move into meteorological spring, can we expect the weather to stay settled? Darren Bett has the long-range forecast.", "filename": "weather_articles_c2013rqdg71o_1745654488.html", "image_url": "https://ichef.bbci.co.uk/ace/branded_weather/1200/cpsprodpb/7830/live/37b78f70-f520-11ef-896e-d7e7fb1719a4.jpg", "language": "en", "localpath": "C:\\Users\\vopha/news-please-repo//data/2025/04/26/bbc.co.uk/weather_articles_c2013rqdg71o_1745654488.html", "title": "Weather for the week ahead", "title_page": "Weather for the week ahead  - BBC Weather", "title_rss": "NULL", "source_domain": "bbc.co.uk", "maintext": "Published\n26 February 2025\nUpdated 27 February 2025\nAs we move into meteorological spring, can we expect the weather to stay settled? Darren Bett has the long-range forecast.", "url": "https://www.bbc.co.uk/weather/articles/c2013rqdg71o"}